LICENSE
README.md
setup.cfg
setup.py
versioneer.py
snub/__init__.py
snub/__main__.py
snub/_version.py
snub/gui/__init__.py
snub/gui/main.py
snub/gui/help/__init__.py
snub/gui/help/annotator.md
snub/gui/help/heatmaps.md
snub/gui/help/help_menu.py
snub/gui/help/layout.md
snub/gui/help/loading_data.md
snub/gui/help/scatter_plots.md
snub/gui/help/selections.md
snub/gui/help/timeline.md
snub/gui/help/trace_plots.md
snub/gui/help/video.md
snub/gui/icons/app_icon.png
snub/gui/icons/checkbox_checked.png
snub/gui/icons/checkbox_unchecked.png
snub/gui/icons/minus.png
snub/gui/icons/pause.png
snub/gui/icons/play.png
snub/gui/icons/plus.png
snub/gui/icons/x.png
snub/gui/panels/__init__.py
snub/gui/panels/base.py
snub/gui/panels/pose3D.py
snub/gui/panels/roi.py
snub/gui/panels/scatter.py
snub/gui/panels/video.py
snub/gui/stacks/__init__.py
snub/gui/stacks/base.py
snub/gui/stacks/panel.py
snub/gui/stacks/track.py
snub/gui/tracks/__init__.py
snub/gui/tracks/annotator.py
snub/gui/tracks/base.py
snub/gui/tracks/heatmap.py
snub/gui/tracks/spike.py
snub/gui/tracks/trace.py
snub/gui/utils/__init__.py
snub/gui/utils/interval.py
snub/gui/utils/widgets.py
snub/io/__init__.py
snub/io/manifold.py
snub/io/nwb.py
snub/io/plot.py
snub/io/project.py
snub/io/video.py
systems_neuro_browser.egg-info/PKG-INFO
systems_neuro_browser.egg-info/SOURCES.txt
systems_neuro_browser.egg-info/dependency_links.txt
systems_neuro_browser.egg-info/entry_points.txt
systems_neuro_browser.egg-info/requires.txt
systems_neuro_browser.egg-info/top_level.txt
tests/test_gui.py
tests/test_io.py
tests/test_nwb.py