Metadata-Version: 2.1
Name: systems-neuro-browser
Version: 0.1.2
Summary: Systems Neuro Browser
Home-page: https://github.com/calebweinreb/SNUB
Author: Caleb Weinreb
Author-email: calebsw@gmail.com
Classifier: Programming Language :: Python :: 3
Classifier: Operating System :: OS Independent
Requires-Python: >=3.8
License-File: LICENSE
Requires-Dist: PyQt5
Requires-Dist: numpy
Requires-Dist: scikit-learn
Requires-Dist: tqdm
Requires-Dist: cmapy
Requires-Dist: interlap
Requires-Dist: numba
Requires-Dist: vispy
Requires-Dist: imageio
Requires-Dist: imageio-ffmpeg
Requires-Dist: umap-learn
Requires-Dist: rastermap==0.1.3
Requires-Dist: ipykernel
Requires-Dist: pyqtgraph
Requires-Dist: networkx
Requires-Dist: opencv-python; python_version > "3.8"
Requires-Dist: opencv-python==4.1.2.30; python_version == "3.8"
Requires-Dist: vidio>=0.0.3
Requires-Dist: pynwb
Requires-Dist: ndx-pose
Requires-Dist: ndx-photometry
Requires-Dist: ndx-depth-moseq
Requires-Dist: pandas
Requires-Dist: dandi
Requires-Dist: markdown
Requires-Dist: PyQtWebEngine
Provides-Extra: dev
Requires-Dist: pytest; extra == "dev"
Requires-Dist: black; extra == "dev"
Requires-Dist: pytest-qt; extra == "dev"
Requires-Dist: sphinx==4.4.0; extra == "dev"
Requires-Dist: sphinx_rtd_theme==1.0.0; extra == "dev"
